{
	"info": {
		"_postman_id": "234558bf-5250-4578-893a-bfb919c110fd",
		"name": "Demo",
		"schema": "https://schema.getpostman.com/json/collection/v2.1.0/collection.json",
		"_exporter_id": "23215186"
	},
	"item": [
		{
			"name": "List users",
			"protocolProfileBehavior": {
				"disableBodyPruning": true
			},
			"request": {
				"method": "GET",
				"header": [],
				"body": {
					"mode": "raw",
					"raw": "",
					"options": {
						"raw": {
							"language": "json"
						}
					}
				},
				"url": {
					"raw": "{{baseurl}}/api/users",
					"host": [
						"{{baseurl}}"
					],
					"path": [
						"api",
						"users"
					]
				}
			},
			"response": []
		},
		{
			"name": "Single user by id",
			"protocolProfileBehavior": {
				"disableBodyPruning": true
			},
			"request": {
				"method": "GET",
				"header": [],
				"body": {
					"mode": "raw",
					"raw": "",
					"options": {
						"raw": {
							"language": "json"
						}
					}
				},
				"url": {
					"raw": "{{baseurl}}/api/users/2",
					"host": [
						"{{baseurl}}"
					],
					"path": [
						"api",
						"users",
						"2"
					]
				}
			},
			"response": []
		},
		{
			"name": "Single user not found",
			"protocolProfileBehavior": {
				"disableBodyPruning": true
			},
			"request": {
				"method": "GET",
				"header": [],
				"body": {
					"mode": "raw",
					"raw": "",
					"options": {
						"raw": {
							"language": "json"
						}
					}
				},
				"url": {
					"raw": "{{baseurl}}/api/users/26",
					"host": [
						"{{baseurl}}"
					],
					"path": [
						"api",
						"users",
						"26"
					]
				}
			},
			"response": []
		},
		{
			"name": "List resource",
			"protocolProfileBehavior": {
				"disableBodyPruning": true
			},
			"request": {
				"method": "GET",
				"header": [],
				"body": {
					"mode": "raw",
					"raw": "",
					"options": {
						"raw": {
							"language": "json"
						}
					}
				},
				"url": {
					"raw": "{{baseurl}}/api/unknown",
					"host": [
						"{{baseurl}}"
					],
					"path": [
						"api",
						"unknown"
					]
				}
			},
			"response": []
		},
		{
			"name": "Get single resource by id",
			"protocolProfileBehavior": {
				"disableBodyPruning": true
			},
			"request": {
				"method": "GET",
				"header": [],
				"body": {
					"mode": "raw",
					"raw": "",
					"options": {
						"raw": {
							"language": "json"
						}
					}
				},
				"url": {
					"raw": "{{baseurl}}/api/unknown/3",
					"host": [
						"{{baseurl}}"
					],
					"path": [
						"api",
						"unknown",
						"3"
					]
				}
			},
			"response": []
		},
		{
			"name": "Get Single resource not found",
			"protocolProfileBehavior": {
				"disableBodyPruning": true
			},
			"request": {
				"method": "GET",
				"header": [],
				"body": {
					"mode": "raw",
					"raw": "",
					"options": {
						"raw": {
							"language": "json"
						}
					}
				},
				"url": {
					"raw": "{{baseurl}}/api/unknown/23",
					"host": [
						"{{baseurl}}"
					],
					"path": [
						"api",
						"unknown",
						"23"
					]
				}
			},
			"response": []
		},
		{
			"name": "Create user",
			"request": {
				"method": "POST",
				"header": [],
				"body": {
					"mode": "raw",
					"raw": "{\r\n    \"name\": \"morpheus\",\r\n    \"job\": \"leader\"\r\n}",
					"options": {
						"raw": {
							"language": "json"
						}
					}
				},
				"url": {
					"raw": "{{baseurl}}/api/users",
					"host": [
						"{{baseurl}}"
					],
					"path": [
						"api",
						"users"
					]
				}
			},
			"response": []
		},
		{
			"name": "Update user by id POST",
			"request": {
				"method": "POST",
				"header": [],
				"body": {
					"mode": "raw",
					"raw": "{\r\n    \"name\": \"morpheus\",\r\n    \"job\": \"zion resident\"\r\n}",
					"options": {
						"raw": {
							"language": "json"
						}
					}
				},
				"url": {
					"raw": "{{baseurl}}/api/users/483",
					"host": [
						"{{baseurl}}"
					],
					"path": [
						"api",
						"users",
						"483"
					]
				}
			},
			"response": []
		},
		{
			"name": "Update user by id PATCH",
			"request": {
				"method": "PATCH",
				"header": [],
				"body": {
					"mode": "raw",
					"raw": "{\r\n    \"name\": \"morpheus\",\r\n    \"job\": \"zion resident\"\r\n}",
					"options": {
						"raw": {
							"language": "json"
						}
					}
				},
				"url": {
					"raw": "{{baseurl}}/api/users/483",
					"host": [
						"{{baseurl}}"
					],
					"path": [
						"api",
						"users",
						"483"
					]
				}
			},
			"response": []
		},
		{
			"name": "Delete user by id",
			"request": {
				"method": "DELETE",
				"header": [],
				"body": {
					"mode": "raw",
					"raw": "",
					"options": {
						"raw": {
							"language": "json"
						}
					}
				},
				"url": {
					"raw": "{{baseurl}}/api/users/1",
					"host": [
						"{{baseurl}}"
					],
					"path": [
						"api",
						"users",
						"1"
					]
				}
			},
			"response": []
		},
		{
			"name": "Register successful",
			"request": {
				"method": "POST",
				"header": [],
				"body": {
					"mode": "raw",
					"raw": "{\r\n    \"email\": \"eve.holt@reqres.in\",\r\n    \"password\": \"pistol\"\r\n}",
					"options": {
						"raw": {
							"language": "json"
						}
					}
				},
				"url": {
					"raw": "{{baseurl}}/api/register",
					"host": [
						"{{baseurl}}"
					],
					"path": [
						"api",
						"register"
					]
				}
			},
			"response": []
		},
		{
			"name": "Register unsuccessful",
			"request": {
				"method": "POST",
				"header": [],
				"body": {
					"mode": "raw",
					"raw": "{\r\n    \"email\": \"peter@klaven\"\r\n}\r\n",
					"options": {
						"raw": {
							"language": "json"
						}
					}
				},
				"url": {
					"raw": "{{baseurl}}/api/register",
					"host": [
						"{{baseurl}}"
					],
					"path": [
						"api",
						"register"
					]
				}
			},
			"response": []
		},
		{
			"name": "Login Successful",
			"request": {
				"method": "POST",
				"header": [],
				"body": {
					"mode": "raw",
					"raw": "{\r\n    \"email\": \"eve.holt@reqres.in\",\r\n    \"password\": \"cityslicka\"\r\n}",
					"options": {
						"raw": {
							"language": "json"
						}
					}
				},
				"url": {
					"raw": "{{baseurl}}/api/login",
					"host": [
						"{{baseurl}}"
					],
					"path": [
						"api",
						"login"
					]
				}
			},
			"response": []
		},
		{
			"name": "Login unsuccessful",
			"request": {
				"method": "POST",
				"header": [],
				"body": {
					"mode": "raw",
					"raw": "{\r\n    \"email\": \"peter@klaven\"\r\n}",
					"options": {
						"raw": {
							"language": "json"
						}
					}
				},
				"url": {
					"raw": "{{baseurl}}/api/login",
					"host": [
						"{{baseurl}}"
					],
					"path": [
						"api",
						"login"
					]
				}
			},
			"response": []
		},
		{
			"name": "Get delayed Response",
			"protocolProfileBehavior": {
				"disableBodyPruning": true
			},
			"request": {
				"method": "GET",
				"header": [],
				"body": {
					"mode": "raw",
					"raw": "",
					"options": {
						"raw": {
							"language": "json"
						}
					}
				},
				"url": {
					"raw": "{{baseurl}}/api/users?delay=4",
					"host": [
						"{{baseurl}}"
					],
					"path": [
						"api",
						"users"
					],
					"query": [
						{
							"key": "delay",
							"value": "4"
						}
					]
				}
			},
			"response": []
		}
	]
}